<?xml version="1.0" encoding="UTF-8"?>
<contactLists xmlns:xsi="http://www.w3.org/2001/XMLSchema-instance" xsi:noNamespaceSchemaLocation="contactListSchema.xsd"><contact><id>144417131527</id><image>tgrtgfg54c5rtfr5</image><firstName>tgrtgfg54c5rtfr5</firstName><lastName/><gender>M</gender><nickName>blais M</nickName><dateOfBirth/><postalDetails><city/><street/><postalCode/><country>Mauritius</country></postalDetails><emails><officeEmail/><privateEmail/></emails><telephoneNumbers><privateMobile/><office/></telephoneNumbers></contact></contactLists>
